{
  "$schema": "https://developer.microsoft.com/json-schemas/fabric/item/report/definition/visualContainer/2.10.0/schema.json",
  "name": "a6856e74e4094141a05b",
  "position": {
    "x": 430.12987012987014,
    "y": 340.77922077922079,
    "z": 14000,
    "height": 700.25974025974028,
    "width": 1433.7662337662337,
    "tabOrder": 14000
  },
  "visual": {
    "visualType": "pivotTable",
    "query": {
      "queryState": {
        "Rows": {
          "projections": [
            {
              "field": {
                "Column": {
                  "Expression": {
                    "SourceRef": {
                      "Entity": "validationresults"
                    }
                  },
                  "Property": "validation_type"
                }
              },
              "queryRef": "validationresults.validation_type",
              "nativeQueryRef": "validation_type",
              "active": true
            },
            {
              "field": {
                "Column": {
                  "Expression": {
                    "SourceRef": {
                      "Entity": "validationresults"
                    }
                  },
                  "Property": "check_item"
                }
              },
              "queryRef": "validationresults.check_item",
              "nativeQueryRef": "check_item",
              "active": true
            }
          ]
        },
        "Values": {
          "projections": [
            {
              "field": {
                "Measure": {
                  "Expression": {
                    "SourceRef": {
                      "Entity": "_measure"
                    }
                  },
                  "Property": "Total DQ"
                }
              },
              "queryRef": "_measure.Total DQ",
              "nativeQueryRef": "Total DQ"
            },
            {
              "field": {
                "Measure": {
                  "Expression": {
                    "SourceRef": {
                      "Entity": "_measure"
                    }
                  },
                  "Property": "DQ Score"
                }
              },
              "queryRef": "_measure.DQ Score",
              "nativeQueryRef": "DQ Score"
            },
            {
              "field": {
                "Measure": {
                  "Expression": {
                    "SourceRef": {
                      "Entity": "_measure"
                    }
                  },
                  "Property": "Gold DQ Status"
                }
              },
              "queryRef": "_measure.Gold DQ Status",
              "nativeQueryRef": "Gold DQ Status"
            }
          ]
        }
      }
    },
    "expansionStates": [
      {
        "roles": [
          "Rows"
        ],
        "levels": [
          {
            "queryRefs": [
              "validationresults.validation_type"
            ],
            "isCollapsed": true,
            "identityKeys": [
              {
                "Column": {
                  "Expression": {
                    "SourceRef": {
                      "Entity": "validationresults"
                    }
                  },
                  "Property": "validation_type"
                }
              }
            ],
            "isPinned": true
          },
          {
            "queryRefs": [
              "validationresults.check_item"
            ],
            "isCollapsed": true,
            "isPinned": true
          }
        ],
        "root": {
          "children": [
            {
              "identityValues": [
                {
                  "Literal": {
                    "Value": "'Grain Validation'"
                  }
                }
              ],
              "isToggled": true
            }
          ]
        }
      }
    ],
    "objects": {
      "subTotals": [
        {
          "properties": {
            "rowSubtotals": {
              "expr": {
                "Literal": {
                  "Value": "false"
                }
              }
            },
            "columnSubtotals": {
              "expr": {
                "Literal": {
                  "Value": "false"
                }
              }
            },
            "perRowLevel": {
              "expr": {
                "Literal": {
                  "Value": "false"
                }
              }
            }
          }
        }
      ],
      "values": [
        {
          "properties": {
            "fontSize": {
              "expr": {
                "Literal": {
                  "Value": "15D"
                }
              }
            },
            "fontFamily": {
              "expr": {
                "Literal": {
                  "Value": "'''Segoe UI'', wf_segoe-ui_normal, helvetica, arial, sans-serif'"
                }
              }
            }
          }
        },
        {
          "properties": {
            "fontColor": {
              "solid": {
                "color": {
                  "expr": {
                    "Conditional": {
                      "Cases": [
                        {
                          "Condition": {
                            "Comparison": {
                              "ComparisonKind": 0,
                              "Left": {
                                "Measure": {
                                  "Expression": {
                                    "SourceRef": {
                                      "Entity": "_measure"
                                    }
                                  },
                                  "Property": "Gold DQ Status"
                                }
                              },
                              "Right": {
                                "Literal": {
                                  "Value": "'PASS'"
                                }
                              }
                            },
                            "Annotations": {
                              "PowerBI.SQExprEvaluationKind": 1,
                              "PowerBI.SQExprTextOperatorOption": 2
                            }
                          },
                          "Value": {
                            "Literal": {
                              "Value": "'#0E6B0E'"
                            }
                          }
                        },
                        {
                          "Condition": {
                            "Comparison": {
                              "ComparisonKind": 0,
                              "Left": {
                                "Measure": {
                                  "Expression": {
                                    "SourceRef": {
                                      "Entity": "_measure"
                                    }
                                  },
                                  "Property": "Gold DQ Status"
                                }
                              },
                              "Right": {
                                "Literal": {
                                  "Value": "'FAIL'"
                                }
                              }
                            },
                            "Annotations": {
                              "PowerBI.SQExprEvaluationKind": 1,
                              "PowerBI.SQExprTextOperatorOption": 2
                            }
                          },
                          "Value": {
                            "Literal": {
                              "Value": "'#A1343C'"
                            }
                          }
                        }
                      ]
                    }
                  }
                }
              }
            }
          },
          "selector": {
            "data": [
              {
                "dataViewWildcard": {
                  "matchingOption": 1
                }
              }
            ],
            "metadata": "_measure.Gold DQ Status"
          }
        }
      ],
      "columnHeaders": [
        {
          "properties": {
            "fontSize": {
              "expr": {
                "Literal": {
                  "Value": "15D"
                }
              }
            },
            "fontFamily": {
              "expr": {
                "Literal": {
                  "Value": "'''Segoe UI'', wf_segoe-ui_normal, helvetica, arial, sans-serif'"
                }
              }
            },
            "bold": {
              "expr": {
                "Literal": {
                  "Value": "true"
                }
              }
            },
            "columnAdjustment": {
              "expr": {
                "Literal": {
                  "Value": "'growToFit'"
                }
              }
            }
          }
        }
      ],
      "rowHeaders": [
        {
          "properties": {
            "fontSize": {
              "expr": {
                "Literal": {
                  "Value": "15D"
                }
              }
            },
            "bold": {
              "expr": {
                "Literal": {
                  "Value": "false"
                }
              }
            }
          }
        }
      ],
      "general": [
        {
          "properties": {
            "layout": {
              "expr": {
                "Literal": {
                  "Value": "'Compact'"
                }
              }
            }
          }
        }
      ],
      "grid": [
        {
          "properties": {}
        }
      ],
      "columnFormatting": [
        {
          "properties": {
            "alignment": {
              "expr": {
                "Literal": {
                  "Value": "'Center'"
                }
              }
            }
          },
          "selector": {
            "metadata": "_measure.Gold DQ Status"
          }
        }
      ]
    },
    "visualContainerObjects": {
      "stylePreset": [
        {
          "properties": {
            "name": {
              "expr": {
                "Literal": {
                  "Value": "'Minimal'"
                }
              }
            }
          }
        }
      ]
    },
    "drillFilterOtherVisuals": true
  }
}