{
  "$schema": "https://developer.microsoft.com/json-schemas/fabric/item/report/definition/visualContainer/2.10.0/schema.json",
  "name": "e210393fc9e075ba00c8",
  "position": {
    "x": 982,
    "y": 190,
    "z": 10000,
    "height": 161,
    "width": 440,
    "tabOrder": 10000
  },
  "visual": {
    "visualType": "cardVisual",
    "query": {
      "queryState": {
        "Data": {
          "projections": [
            {
              "field": {
                "Aggregation": {
                  "Expression": {
                    "Column": {
                      "Expression": {
                        "SourceRef": {
                          "Entity": "factpolicy"
                        }
                      },
                      "Property": "policy_premium_amount"
                    }
                  },
                  "Function": 1
                }
              },
              "queryRef": "Sum(factpolicy.policy_premium_amount)",
              "nativeQueryRef": "Average Premium",
              "displayName": "Average Premium",
              "format": "#,0.00 \"₫\";-#,0.00 \"₫\";#,0.00 \"₫\""
            }
          ]
        }
      },
      "sortDefinition": {
        "sort": [
          {
            "field": {
              "Aggregation": {
                "Expression": {
                  "Column": {
                    "Expression": {
                      "SourceRef": {
                        "Entity": "factpolicy"
                      }
                    },
                    "Property": "policy_premium_amount"
                  }
                },
                "Function": 1
              }
            },
            "direction": "Descending"
          }
        ],
        "isDefaultSort": true
      }
    },
    "objects": {
      "value": [
        {
          "properties": {
            "bold": {
              "expr": {
                "Literal": {
                  "Value": "true"
                }
              }
            },
            "fontFamily": {
              "expr": {
                "Literal": {
                  "Value": "'''Arial Black'''"
                }
              }
            },
            "fontColor": {
              "solid": {
                "color": {
                  "expr": {
                    "Literal": {
                      "Value": "'#6A1F7A'"
                    }
                  }
                }
              }
            },
            "fontSize": {
              "expr": {
                "Literal": {
                  "Value": "35D"
                }
              }
            },
            "horizontalAlignment": {
              "expr": {
                "Literal": {
                  "Value": "'center'"
                }
              }
            }
          },
          "selector": {
            "id": "default"
          }
        }
      ],
      "label": [
        {
          "properties": {
            "fontColor": {
              "solid": {
                "color": {
                  "expr": {
                    "Literal": {
                      "Value": "'#6A1F7A'"
                    }
                  }
                }
              }
            },
            "fontSize": {
              "expr": {
                "Literal": {
                  "Value": "18D"
                }
              }
            },
            "fontFamily": {
              "expr": {
                "Literal": {
                  "Value": "'Arial'"
                }
              }
            }
          },
          "selector": {
            "id": "default"
          }
        }
      ],
      "divider": [
        {
          "properties": {
            "show": {
              "expr": {
                "Literal": {
                  "Value": "false"
                }
              }
            }
          },
          "selector": {
            "id": "default"
          }
        }
      ],
      "fillCustom": [
        {
          "properties": {
            "show": {
              "expr": {
                "Literal": {
                  "Value": "false"
                }
              }
            }
          }
        }
      ],
      "outline": [
        {
          "properties": {
            "show": {
              "expr": {
                "Literal": {
                  "Value": "false"
                }
              }
            },
            "lineColor": {
              "solid": {
                "color": {
                  "expr": {
                    "Literal": {
                      "Value": "'#6A1F7A'"
                    }
                  }
                }
              }
            }
          },
          "selector": {
            "id": "default"
          }
        }
      ],
      "padding": [
        {
          "properties": {
            "paddingUniform": {
              "expr": {
                "Literal": {
                  "Value": "6L"
                }
              }
            }
          },
          "selector": {
            "id": "default"
          }
        }
      ],
      "border": [
        {
          "properties": {
            "show": {
              "expr": {
                "Literal": {
                  "Value": "false"
                }
              }
            },
            "color": {
              "solid": {
                "color": {
                  "expr": {
                    "Literal": {
                      "Value": "'#6A1F7A'"
                    }
                  }
                }
              }
            }
          },
          "selector": {
            "id": "default"
          }
        }
      ],
      "layout": [
        {
          "properties": {
            "paddingUniform": {
              "expr": {
                "Literal": {
                  "Value": "0L"
                }
              }
            }
          },
          "selector": {
            "id": "default"
          }
        }
      ]
    },
    "visualContainerObjects": {
      "padding": [
        {
          "properties": {
            "bottom": {
              "expr": {
                "Literal": {
                  "Value": "0D"
                }
              }
            },
            "right": {
              "expr": {
                "Literal": {
                  "Value": "0D"
                }
              }
            },
            "top": {
              "expr": {
                "Literal": {
                  "Value": "0D"
                }
              }
            },
            "left": {
              "expr": {
                "Literal": {
                  "Value": "0D"
                }
              }
            }
          }
        }
      ],
      "border": [
        {
          "properties": {
            "show": {
              "expr": {
                "Literal": {
                  "Value": "true"
                }
              }
            },
            "radius": {
              "expr": {
                "Literal": {
                  "Value": "8D"
                }
              }
            },
            "width": {
              "expr": {
                "Literal": {
                  "Value": "2D"
                }
              }
            },
            "color": {
              "solid": {
                "color": {
                  "expr": {
                    "Literal": {
                      "Value": "'#6A1F7A'"
                    }
                  }
                }
              }
            }
          }
        }
      ]
    },
    "drillFilterOtherVisuals": true
  },
  "filterConfig": {
    "filters": [
      {
        "name": "fe3be8d342de059e574d",
        "field": {
          "Aggregation": {
            "Expression": {
              "Column": {
                "Expression": {
                  "SourceRef": {
                    "Entity": "factpolicy"
                  }
                },
                "Property": "policy_premium_amount"
              }
            },
            "Function": 1
          }
        },
        "type": "Advanced"
      }
    ]
  }
}